{
  "name": "火基調速攻",
  "cards": [
    {
      "id": "dm26-rp2.U.42/77",
      "count": 4
    },
    {
      "id": "dm26-rp2.U.41/77",
      "count": 4
    },
    {
      "id": "dm26-rp1.VR.5/77",
      "count": 4
    },
    {
      "id": "dm26-rp2.R.18/77",
      "count": 4
    },
    {
      "id": "dm26-rp1.UC.42/77",
      "count": 4
    },
    {
      "id": "dm26-rp2.U.43/77",
      "count": 4
    },
    {
      "id": "dm26-rp1.R.19/77",
      "count": 4
    },
    {
      "id": "dm26-rp2.SR.S5/S11",
      "count": 4
    },
    {
      "id": "dm26-rp1.SR.S7/S11",
      "count": 4
    },
    {
      "id": "dm26-rp1.UC.40/77",
      "count": 4
    }
  ]
}